README.md
setup.py
luigi_poltergust.egg-info/PKG-INFO
luigi_poltergust.egg-info/SOURCES.txt
luigi_poltergust.egg-info/dependency_links.txt
luigi_poltergust.egg-info/requires.txt
luigi_poltergust.egg-info/top_level.txt
poltergust/__init__.py
poltergust/testx.py