Metadata-Version: 2.1
Name: luigi-poltergust
Version: 0.0.4
Summary: Task trigger for Luigi
Home-page: https://github.com/emerald-geomodelling/poltergust
Author: Egil Moeller
Author-email: em@emrld.no
License: UNKNOWN
Platform: UNKNOWN
